hein_hplc/__init__.py
hein_hplc/app.py
hein_hplc/assets/favicon.ico
hein_hplc/assets/logo.png
hein_hplc/peak_analysis/__init__.py
hein_hplc/peak_analysis/peak_analysis_main.py
hein_hplc/peak_analysis/peak_deconvolution.py
hein_hplc/peak_analysis/utils.py
hein_hplc-0.2.6.dist-info/LICENSE
hein_hplc-0.2.6.dist-info/METADATA
hein_hplc-0.2.6.dist-info/WHEEL
hein_hplc-0.2.6.dist-info/entry_points.txt
hein_hplc-0.2.6.dist-info/top_level.txt
hein_hplc-0.2.6.dist-info/RECORD
