Metadata-Version: 2.1
Name: hein-hplc
Version: 0.2.6
Summary: This web app analyze deconvoluted HPLC peaks and plot time course data
Home-page: https://gitlab.com/heingroup/hein-hplc
Author: Ivory Zhang
Author-email: ivoryzhang@chem.ubc.ca
License: MIT
License-File: LICENSE
Requires-Dist: dash-bootstrap-components
Requires-Dist: pandas
Requires-Dist: scipy
Requires-Dist: plotly
Requires-Dist: numpy
Requires-Dist: rainbow-api
